rpdk/python/__init__.py
rpdk/python/codegen.py
rpdk/python/parser.py
rpdk/python/resolver.py
rpdk/python/data/Python.gitignore
rpdk/python/data/__init__.py
rpdk/python/templates/README.md
rpdk/python/templates/handlers.py
rpdk/python/templates/hook_handlers.py
rpdk/python/templates/hook_models.py
rpdk/python/templates/models.py
rpdk/python/templates/requirements.txt
rpdk/python/templates/target_model.py
cloudformation_cli_python_plugin-2.1.10.dist-info/LICENSE
cloudformation_cli_python_plugin-2.1.10.dist-info/METADATA
cloudformation_cli_python_plugin-2.1.10.dist-info/WHEEL
cloudformation_cli_python_plugin-2.1.10.dist-info/entry_points.txt
cloudformation_cli_python_plugin-2.1.10.dist-info/top_level.txt
cloudformation_cli_python_plugin-2.1.10.dist-info/zip-safe
cloudformation_cli_python_plugin-2.1.10.dist-info/RECORD
